EasyToCacheLib/__init__.py
EasyToCacheLib/easy_to_cache.py
EasyToCacheLib/etc_infrastructure.py
EasyToCacheLib/json_exp.py
EasyToCacheLib/tests.py
EasyToCache-0.0.9.dist-info/METADATA
EasyToCache-0.0.9.dist-info/WHEEL
EasyToCache-0.0.9.dist-info/top_level.txt
EasyToCache-0.0.9.dist-info/RECORD
