Metadata-Version: 2.1
Name: EasyToCache
Version: 0.0.9
Summary: This is simple module to cache using json.
Home-page: https://github.com/M1KoDam/EasyToCacheLib
Author: MikoDam
Author-email: kononov.mixa2045@gmail.com
Project-URL: GitHub, https://github.com/M1KoDam/EasyToCacheLib
Keywords: files cache json
Classifier: Programming Language :: Python :: 3.10
Classifier: License :: OSI Approved :: MIT License
Classifier: Operating System :: OS Independent
Requires-Python: >=3.10
